README
setup.cfg
setup.py
demo/__init__.py
pkgdemo.egg-info/PKG-INFO
pkgdemo.egg-info/SOURCES.txt
pkgdemo.egg-info/dependency_links.txt
pkgdemo.egg-info/entry_points.txt
pkgdemo.egg-info/namespace_packages.txt
pkgdemo.egg-info/requires.txt
pkgdemo.egg-info/top_level.txt