Metadata-Version: 1.1
Name: pkgdemo
Version: 0.1.1
Summary: It's my first package,I'm a chinese
Home-page: UNKNOWN
Author: Fanglei.Zou(1981)
Author-email: UNKNOWN
License: GPL
Platform: UNKNOWN
Classifier: Programming Language :: Python
Classifier: Topic :: Software Development :: Libraries :: Python Modules
